{
  "parent": "minecraft:recipes/root",
  "rewards": {
    "recipes": [
      "minecraft:repeater"
    ]
  },
  "criteria": {
    "has_redstone_dust": {
      "trigger": "minecraft:inventory_changed",
      "conditions": {
        "items": [
          {
            "tag": "forge:dusts/redstone"
          }
        ]
      }
    },
    "has_copper_ingot": {
      "trigger": "minecraft:inventory_changed",
      "conditions": {
        "items": [
          {
            "tag": "forge:ingots/copper"
          }
        ]
      }
    },
    "has_the_recipe": {
      "trigger": "minecraft:recipe_unlocked",
      "conditions": {
        "recipe": "minecraft:repeater"
      }
    }
  },
  "requirements": [
    [
      "has_redstone_dust",
      "has_copper_ingot",
      "has_the_recipe"
    ]
  ]
}